ai/backend/web/VERSION
ai/backend/web/__init__.py
ai/backend/web/auth.py
ai/backend/web/logging.py
ai/backend/web/proxy.py
ai/backend/web/py.typed
ai/backend/web/response.py
ai/backend/web/security.py
ai/backend/web/server.py
ai/backend/web/stats.py
ai/backend/web/template.py
ai/backend/web/cli/__init__.py
ai/backend/web/cli/__main__.py
ai/backend/web/cli/config.py
ai/backend/web/cli/context.py
ai/backend/web/config/__init__.py
ai/backend/web/config/unified.py
ai/backend/web/static/asset-manifest.json
ai/backend/web/static/config.toml
ai/backend/web/static/index.html
ai/backend/web/static/manifest.json
ai/backend/web/static/sw.js
ai/backend/web/static/sw.js.map
ai/backend/web/static/version.json
ai/backend/web/static/workbox-ed9981e3.js
ai/backend/web/static/workbox-ed9981e3.js.map
ai/backend/web/static/dist/components/backend-ai-change-forgot-password-view-bZdNdE8_.js
ai/backend/web/static/dist/components/backend-ai-edu-applauncher-CGR4wXFN.js
ai/backend/web/static/dist/components/backend-ai-email-verification-view-D-a1yrFE.js
ai/backend/web/static/dist/components/backend-ai-error-view-CC5SP6HD.js
ai/backend/web/static/dist/components/backend-ai-import-view-CqO488ov.js
ai/backend/web/static/dist/components/backend-ai-permission-denied-view-DvgZSn1f.js
ai/backend/web/static/dist/components/backend-ai-resource-monitor-DoqSoK0-.js
ai/backend/web/static/dist/components/backend-ai-serving-view-BmyvymMU.js
ai/backend/web/static/dist/components/backend-ai-session-view-DHp67Ism.js
ai/backend/web/static/dist/components/backend-ai-summary-view-BieERrXQ.js
ai/backend/web/static/dist/components/backend-ai-webui-CPEM64Mv.js
ai/backend/web/static/dist/components/backend-ai-webui.js
ai/backend/web/static/dist/components/lablup-activity-panel-CNBaJuF-.js
ai/backend/web/static/manifest/app.js
ai/backend/web/static/manifest/backend-ai.icns
ai/backend/web/static/manifest/backend-ai.ico
ai/backend/web/static/manifest/backend.ai-brand-simple-bgdark.svg
backend_ai_webserver-25.15.2.dist-info/METADATA
backend_ai_webserver-25.15.2.dist-info/WHEEL
backend_ai_webserver-25.15.2.dist-info/entry_points.txt
backend_ai_webserver-25.15.2.dist-info/namespace_packages.txt
backend_ai_webserver-25.15.2.dist-info/top_level.txt
backend_ai_webserver-25.15.2.dist-info/RECORD
