Metadata-Version: 2.4
Name: backend.ai-webserver
Version: 25.15.2
Summary: Backend.AI WebUI Host
Home-page: https://github.com/lablup/backend.ai
Author: Lablup Inc. and contributors
License: LGPLv3
Project-URL: Documentation, https://docs.backend.ai/
Project-URL: Source, https://github.com/lablup/backend.ai
Classifier: Intended Audience :: Developers
Classifier: Operating System :: MacOS :: MacOS X
Classifier: Operating System :: POSIX :: Linux
Classifier: Programming Language :: Python
Classifier: Programming Language :: Python :: 3
Classifier: Environment :: No Input/Output (Daemon)
Classifier: Topic :: Scientific/Engineering
Classifier: Topic :: Software Development
Classifier: Development Status :: 5 - Production/Stable
Classifier: Programming Language :: Python :: 3.13
Classifier: License :: OSI Approved :: GNU Lesser General Public License v3 or later (LGPLv3+)
Requires-Python: >=3.13,<3.14
Requires-Dist: Jinja2~=3.1.6
Requires-Dist: aiohttp_cors~=0.8.1
Requires-Dist: aiohttp~=3.12.15
Requires-Dist: aiotools~=1.9.0
Requires-Dist: backend.ai-cli==25.15.2
Requires-Dist: backend.ai-client==25.15.2
Requires-Dist: backend.ai-common==25.15.2
Requires-Dist: backend.ai-logging==25.15.2
Requires-Dist: backend.ai-plugin==25.15.2
Requires-Dist: click~=8.1.7
Requires-Dist: coloredlogs~=15.0
Requires-Dist: multidict~=6.6.4
Requires-Dist: pycryptodome>=3.20.0
Requires-Dist: pydantic[email]~=2.11.3
Requires-Dist: setproctitle~=1.3.5
Requires-Dist: tomli~=2.0.1
Requires-Dist: trafaret~=2.1
Requires-Dist: types-Jinja2
Requires-Dist: uvloop~=0.21; sys_platform != "Windows"
Dynamic: author
Dynamic: classifier
Dynamic: description
Dynamic: description-content-type
Dynamic: home-page
Dynamic: license
Dynamic: project-url
Dynamic: requires-dist
Dynamic: requires-python
Dynamic: summary
